build/setup.py
interregnum/__init__.py
interregnum/_version.py
interregnum/bisect.py
interregnum/collections.py
interregnum/dfs.py
interregnum/divisors.py
interregnum/exceptions.py
interregnum/graphs.py
interregnum/logging.py
interregnum/py.typed
interregnum/quotas.py
interregnum/random.py
interregnum/ranks.py
interregnum/rounding.py
interregnum/tabulate.py
interregnum/types.py
interregnum/yaml.py
interregnum/bidimensional/__init__.py
interregnum/bidimensional/dataframe.py
interregnum/bidimensional/matrix.py
interregnum/bidimensional/sparse.py
interregnum/cli/__init__.py
interregnum/cli/__main__.py
interregnum/cli/cmd_calculate.py
interregnum/cli/cmd_dump.py
interregnum/cli/cmd_graph.py
interregnum/cli/cmd_list.py
interregnum/cli/files.py
interregnum/district/__init__.py
interregnum/district/compensatory.py
interregnum/district/contenders.py
interregnum/district/counting.py
interregnum/district/district.py
interregnum/district/group.py
interregnum/district/io.py
interregnum/district/node.py
interregnum/district/reapportionment.py
interregnum/district/references.py
interregnum/district/restriction.py
interregnum/district/serialize.py
interregnum/methods/__init__.py
interregnum/methods/events.py
interregnum/methods/filters.py
interregnum/methods/inputs.py
interregnum/methods/adapters/__init__.py
interregnum/methods/adapters/initialseats.py
interregnum/methods/adapters/maxseats.py
interregnum/methods/adapters/multiwinner.py
interregnum/methods/adapters/ranking.py
interregnum/methods/biproportional/__init__.py
interregnum/methods/biproportional/table.py
interregnum/methods/biproportional/tally.py
interregnum/methods/compensatory/__init__.py
interregnum/methods/compensatory/additional_member.py
interregnum/methods/compensatory/mixed_member.py
interregnum/methods/preferential/__init__.py
interregnum/methods/preferential/borda_count.py
interregnum/methods/preferential/io.py
interregnum/methods/preferential/ties.py
interregnum/methods/preferential/types.py
interregnum-0.3.0.dist-info/licenses/LICENSE
interregnum-0.3.0.dist-info/METADATA
interregnum-0.3.0.dist-info/WHEEL
interregnum-0.3.0.dist-info/entry_points.txt
interregnum-0.3.0.dist-info/top_level.txt
interregnum-0.3.0.dist-info/RECORD
