Metadata-Version: 2.4
Name: interregnum
Version: 0.3.0
Summary: multi-district electoral systems
Author-email: wmj <wmj.py@gmx.com>
License: LGPL-3.0-or-later
Project-URL: BugReports, https://gitlab.com/wesmj/interregnum/-/issues
Project-URL: Source, https://gitlab.com/wesmj/interregnum
Project-URL: Documentation, https://interregnum.readthedocs.io
Keywords: electoral systems,proportional vote,preferential vote,condorcet,dhondt,hare,webster,adams,jefferson,sainte laguë,compensatory systems,huntington hill,bi-proportional system,electoral thresholds,gregory transfers,imperiali,droop,hagenbach bischoff,dean,highest averages,largest remainder,iterative divisor,ranked pairs,borda,copeland,minimax,first past the post,mixed member,levelling seats,additional member,instant run-off
Classifier: Environment :: Console
Classifier: Topic :: Utilities
Classifier: Programming Language :: Python :: 3
Classifier: Programming Language :: Python :: 3.10
Classifier: Programming Language :: Python :: 3.11
Classifier: Programming Language :: Python :: 3.12
Classifier: Programming Language :: Python :: 3.13
Requires-Python: >=3.10
License-File: LICENSE
Requires-Dist: PyYAML
Requires-Dist: typing_extensions
Provides-Extra: test
Requires-Dist: pytest; extra == "test"
Provides-Extra: docs
Requires-Dist: sphinx; extra == "docs"
Requires-Dist: myst-parser; extra == "docs"
Provides-Extra: dev
Requires-Dist: build; extra == "dev"
Requires-Dist: sphinx; extra == "dev"
Requires-Dist: reuse; extra == "dev"
Requires-Dist: interregnum[docs,test]; extra == "dev"
Dynamic: license-file
